packing2porenet/__init__.py
packing2porenet/export.py
packing2porenet/geom.py
packing2porenet/linalg.py
packing2porenet/mesh.py
packing2porenet/network.py
packing2porenet/voronoi.py
packing2porenet/ymport.py
packing2porenet-0.1.2.dist-info/LICENSE
packing2porenet-0.1.2.dist-info/METADATA
packing2porenet-0.1.2.dist-info/WHEEL
packing2porenet-0.1.2.dist-info/top_level.txt
packing2porenet-0.1.2.dist-info/RECORD
