Metadata-Version: 2.1
Name: packing2porenet
Version: 0.1.2
Summary: Python package to compute pore network based on given particle packing
Home-page: https://gitlab.com/stranskyjan/packing2porenet
Author: Jan Stránský
Author-email: honzik.stransky@gmail.com
License: UNKNOWN
Project-URL: Bug Tracker, https://gitlab.com/stranskyjan/packing2porenet/-/issues
Platform: UNKNOWN
Classifier: Programming Language :: Python :: 3
Classifier: License :: OSI Approved :: MIT License
Classifier: Operating System :: OS Independent
Requires-Python: >=3.6
License-File: LICENSE
Requires-Dist: future-typing (>=0.4.1)
Requires-Dist: pyvoro-mmalahe (>=1.3.3)
Requires-Dist: numpy (>=1.19.5)
